git_reviewers/__init__.py
git_reviewers/py.typed
git_reviewers/reviewers.py
git_reviewers-0.13.7.dist-info/LICENSE
git_reviewers-0.13.7.dist-info/METADATA
git_reviewers-0.13.7.dist-info/WHEEL
git_reviewers-0.13.7.dist-info/entry_points.txt
git_reviewers-0.13.7.dist-info/top_level.txt
git_reviewers-0.13.7.dist-info/RECORD
