Metadata-Version: 2.1
Name: git-reviewers
Version: 0.13.7
Summary: Suggest reviewers for your git branch
Author-email: Albert Wang <git@albertyw.com>
License: MIT
Project-URL: Homepage, https://github.com/albertyw/git-reviewers
Keywords: git,code,review,reviewer,log,history
Classifier: Development Status :: 4 - Beta
Classifier: Intended Audience :: Developers
Classifier: Natural Language :: English
Classifier: Topic :: Software Development :: Version Control
Classifier: License :: OSI Approved :: MIT License
Classifier: Programming Language :: Python :: 3
Classifier: Programming Language :: Python :: 3.7
Classifier: Programming Language :: Python :: 3.8
Classifier: Programming Language :: Python :: 3.9
Classifier: Programming Language :: Python :: 3.10
Classifier: Programming Language :: Python :: 3.11
Classifier: Programming Language :: Python :: 3.12
Classifier: Programming Language :: Python :: 3.13
Classifier: Typing :: Typed
Requires-Python: >=3.7
License-File: LICENSE
Provides-Extra: test
Requires-Dist: coverage ==7.6.1 ; extra == 'test'
Requires-Dist: ruff ==0.6.7 ; extra == 'test'
Requires-Dist: mypy ==1.11.2 ; extra == 'test'
